timespans.py
timespans-0.1.0.dist-info/DESCRIPTION.rst
timespans-0.1.0.dist-info/METADATA
timespans-0.1.0.dist-info/RECORD
timespans-0.1.0.dist-info/WHEEL
timespans-0.1.0.dist-info/metadata.json
timespans-0.1.0.dist-info/top_level.txt
