Metadata-Version: 2.0
Name: timespans
Version: 0.1.0
Summary: A library for adding and subtracting datetime spans
Home-page: https://github.com/eugene-katsevman/timespans
Author: Eugene Katsevman
Author-email: eugene.katsevman@gmail.com
License: MIT
Keywords: datetime timedelta timespan span
Platform: UNKNOWN
Classifier: Development Status :: 3 - Alpha
Classifier: Topic :: Utilities
Classifier: License :: OSI Approved :: MIT License
Classifier: Programming Language :: Python :: 2.7
Classifier: Programming Language :: Python :: 3
Classifier: Programming Language :: Python :: 3.2
Classifier: Programming Language :: Python :: 3.3
Classifier: Programming Language :: Python :: 3.4
